voices/__init__.py
voices/cli/__init__.py
voices/cli/slicer.py
voices/cli/tools.py
voices/functions/slicer/__init__.py
voices/functions/slicer/config.py
voices/functions/slicer/interactive/__init__.py
voices/functions/slicer/interactive/interactive.py
voices/functions/slicer/interactive/tracker.py
voices/functions/slicer/text/__init__.py
voices/functions/slicer/text/ass.py
voices/functions/slicer/text/slice.py
voices/functions/tools/uta.py
voices-1.2.0.dist-info/entry_points.txt
voices-1.2.0.dist-info/LICENSE
voices-1.2.0.dist-info/METADATA
voices-1.2.0.dist-info/WHEEL
voices-1.2.0.dist-info/RECORD
